lenskit_auto-0.2.0.dist-info/licenses/LICENSE.md
lkauto/__init__.py
lkauto/lkauto.py
lkauto/algorithms/__init__.py
lkauto/algorithms/als.py
lkauto/algorithms/bias.py
lkauto/algorithms/funksvd.py
lkauto/algorithms/item_knn.py
lkauto/algorithms/svd.py
lkauto/algorithms/user_knn.py
lkauto/ensemble/__init__.py
lkauto/ensemble/ensemble_builder.py
lkauto/ensemble/greedy_ensemble_selection.py
lkauto/explicit/__init__.py
lkauto/explicit/explicit_evaler.py
lkauto/implicit/__init__.py
lkauto/implicit/implicit_evaler.py
lkauto/optimization_strategies/__init__.py
lkauto/optimization_strategies/bayesian_optimization.py
lkauto/optimization_strategies/random_search.py
lkauto/preprocessing/__init__.py
lkauto/preprocessing/preprocessing.py
lkauto/preprocessing/pruning.py
lkauto/utils/__init__.py
lkauto/utils/filer.py
lkauto/utils/get_default_configuration_space.py
lkauto/utils/get_default_configurations.py
lkauto/utils/get_model_from_cs.py
lkauto/utils/logging.py
lkauto/utils/update_top_n_runs.py
lkauto/utils/validation_split.py
tests/README.md
tests/__init__.py
tests/algorithms/__init__.py
tests/algorithms/test_als.py
tests/algorithms/test_bias.py
tests/algorithms/test_funk_svd.py
tests/algorithms/test_item_knn.py
tests/algorithms/test_svd.py
tests/algorithms/test_user_knn.py
tests/utils/__init__.py
tests/utils/test_get_default_configuration_space.py
tests/utils/test_get_default_configurations.py
tests/utils/test_get_model_from_cs.py
tests/utils/test_validation_split.py
utils/__init__.py
lenskit_auto-0.2.0.dist-info/METADATA
lenskit_auto-0.2.0.dist-info/WHEEL
lenskit_auto-0.2.0.dist-info/top_level.txt
lenskit_auto-0.2.0.dist-info/RECORD
