Metadata-Version: 2.4
Name: lenskit-auto
Version: 0.2.0
Summary: LensKit-Auto is built as a wrapper around the Python LensKit recommender-system library. It automates algorithm selection and hyper parameter optimization and can build ensemble models based on the LensKit models.
Home-page: https://github.com/ISG-Siegen/lenskit-auto
Author: Tobias Vente
Author-email: Tobias Vente <tobias.vente@uni-siegen.de>, Youssef Fayad <youssef.fayad@student.uni-siegen.de>, Michael Ekstrand <michaelekstrand@boisestate.edu>
License-Expression: MIT
Project-URL: homepage, https://lenskit-auto.readthedocs.io/en/latest/
Project-URL: source, https://github.com/ISG-Siegen/lenskit-auto
Classifier: Programming Language :: Python :: 3.12
Classifier: Operating System :: OS Independent
Requires-Python: >=3.12, <3.13
License-File: LICENSE.md
Requires-Dist: smac>=2.3.1
Requires-Dist: lenskit>=2025.2.0
Requires-Dist: numpy>=2.2.6
Requires-Dist: pandas>=2.2.3
Requires-Dist: scikit-learn>=1.6.1
Requires-Dist: scipy>=1.15.3
Requires-Dist: numba>=0.61.2
Requires-Dist: typing-extensions>=4.13.2
Requires-Dist: matplotlib>=3.10.0
Provides-Extra: dev
Requires-Dist: conda-lock; extra == "dev"
Requires-Dist: invoke>=1; extra == "dev"
Requires-Dist: requests>=2; extra == "dev"
Requires-Dist: sphinx-autobuild>=2021; extra == "dev"
Requires-Dist: flake8>=7.0.0; extra == "dev"
Requires-Dist: rstcheck; extra == "dev"
Requires-Dist: mypy~=1.0; extra == "dev"
Requires-Dist: coverage>=5.0.0; extra == "dev"
Requires-Dist: pytest-cov>=4.0.0; extra == "dev"
Provides-Extra: test
Requires-Dist: pytest>=8.4.1; extra == "test"
Provides-Extra: doc
Requires-Dist: sphinx>=4.2; extra == "doc"
Requires-Dist: sphinxcontrib-bibtex>=2.0; extra == "doc"
Dynamic: author
Dynamic: home-page
Dynamic: license-file
Dynamic: requires-python
